Metadata-Version: 2.1
Name: multicat
Version: 0.1.1
Summary: Multithread reverse shell listener
Home-page: https://github.com/r3nt0n/multicat
Author: r3nt0n
Author-email: r3nt0n@protonmail.com
License: GNU General Public License v3.0
License-File: LICENSE
